{
  "project_info": {
    "project_number": "415305768618",
    "firebase_url": "https://oriental-c0796.firebaseio.com",
    "project_id": "oriental-c0796",
    "storage_bucket": "oriental-c0796.appspot.com"
  },
  "client": [
    {
      "client_info": {
        "mobilesdk_app_id": "1:415305768618:android:82055cad322135aadc7ad3",
        "android_client_info": {
          "package_name": "com.foodsquare_mobile_app"
        }
      },
      "oauth_client": [
        {
          "client_id": "415305768618-jtgjucmmgth1sk418aosrse4hoon46us.apps.googleusercontent.com",
          "client_type": 1,
          "android_info": {
            "package_name": "com.foodsquare_mobile_app",
            "certificate_hash": "632d2b2ca4785a863740cdbd671b75d0d924b4a9"
          }
        },
        {
          "client_id": "415305768618-5ehirbcfbjg2inpegjv24a27jvu7qgnr.apps.googleusercontent.com",
          "client_type": 3
        }
      ],
      "api_key": [
        {
          "current_key": "AIzaSyD8Kjz5dRLn05i0px6NVWDEvb6quIIvPrQ"
        }
      ],
      "services": {
        "appinvite_service": {
          "other_platform_oauth_client": [
            {
              "client_id": "415305768618-5ehirbcfbjg2inpegjv24a27jvu7qgnr.apps.googleusercontent.com",
              "client_type": 3
            }
          ]
        }
      }
    }
  ],
  "configuration_version": "1"
}